BIT_DL/pytorch/__init__.py
BIT_DL/pytorch/hyperparams.py
BIT_DL/pytorch/module_base.py
BIT_DL/pytorch/__pycache__/__init__.cpython-38.pyc
BIT_DL/pytorch/__pycache__/hyperparams.cpython-38.pyc
BIT_DL/pytorch/__pycache__/module_base.cpython-38.pyc
BIT_DL/pytorch/core/__init__.py
BIT_DL/pytorch/core/attention_mechanism.py
BIT_DL/pytorch/core/attention_mechanism_utils.py
BIT_DL/pytorch/core/cell_wrappers.py
BIT_DL/pytorch/core/layers.py
BIT_DL/pytorch/core/optimization.py
BIT_DL/pytorch/core/regularizers.py
BIT_DL/pytorch/core/__pycache__/__init__.cpython-38.pyc
BIT_DL/pytorch/core/__pycache__/attention_mechanism.cpython-38.pyc
BIT_DL/pytorch/core/__pycache__/attention_mechanism_utils.cpython-38.pyc
BIT_DL/pytorch/core/__pycache__/cell_wrappers.cpython-38.pyc
BIT_DL/pytorch/core/__pycache__/layers.cpython-38.pyc
BIT_DL/pytorch/core/__pycache__/optimization.cpython-38.pyc
BIT_DL/pytorch/core/__pycache__/regularizers.cpython-38.pyc
BIT_DL/pytorch/data/__init__.py
BIT_DL/pytorch/data/data_utils.py
BIT_DL/pytorch/data/embedding.py
BIT_DL/pytorch/data/vocabulary.py
BIT_DL/pytorch/data/__pycache__/__init__.cpython-38.pyc
BIT_DL/pytorch/data/__pycache__/data_utils.cpython-38.pyc
BIT_DL/pytorch/data/__pycache__/embedding.cpython-38.pyc
BIT_DL/pytorch/data/__pycache__/vocabulary.cpython-38.pyc
BIT_DL/pytorch/data/data/__init__.py
BIT_DL/pytorch/data/data/data_base.py
BIT_DL/pytorch/data/data/data_iterators.py
BIT_DL/pytorch/data/data/data_iterators_utils.py
BIT_DL/pytorch/data/data/dataset_utils.py
BIT_DL/pytorch/data/data/mono_text_data.py
BIT_DL/pytorch/data/data/multi_aligned_data.py
BIT_DL/pytorch/data/data/paired_text_data.py
BIT_DL/pytorch/data/data/record_data.py
BIT_DL/pytorch/data/data/sampler.py
BIT_DL/pytorch/data/data/scalar_data.py
BIT_DL/pytorch/data/data/text_data_base.py
BIT_DL/pytorch/data/data/__pycache__/__init__.cpython-38.pyc
BIT_DL/pytorch/data/data/__pycache__/data_base.cpython-38.pyc
BIT_DL/pytorch/data/data/__pycache__/data_iterators.cpython-38.pyc
BIT_framework-0.0.2.dist-info/LICENSE
BIT_framework-0.0.2.dist-info/METADATA
BIT_framework-0.0.2.dist-info/WHEEL
BIT_framework-0.0.2.dist-info/top_level.txt
BIT_framework-0.0.2.dist-info/RECORD
