Metadata-Version: 2.1
Name: BIT-framework
Version: 0.0.2
Summary: A dialog framework
Home-page: https://github.com/WangXinglin/BIT_framework
Author: wxl
Author-email: 847084723@qq.com
License: UNKNOWN
Platform: UNKNOWN
Classifier: License :: OSI Approved :: MIT License
Classifier: Programming Language :: Python
Classifier: Intended Audience :: Developers
Classifier: Operating System :: OS Independent
License-File: LICENSE
